neat_notation-0.6.16.dist-info/METADATA
neat_notation-0.6.16.dist-info/WHEEL
neat_notation/__init__.py
neat_notation/__init__.pyi
neat_notation/py.typed
neat_notation/neat_notation.cpython-39-x86_64-linux-gnu.so
neat_notation-0.6.16.dist-info/RECORD
