Metadata-Version: 2.1
Name: neat_notation
Version: 0.6.16
Classifier: Programming Language :: Rust
Classifier: Programming Language :: Python :: Implementation :: CPython
Classifier: Programming Language :: Python :: Implementation :: PyPy
Classifier: License :: OSI Approved :: MIT License
Summary: A smart, modular and readable configuration file format for complex multifile solutions.
Author-email: William A. Lim <frewtypebbles@gmail.com>
Requires-Python: >=3.7
Project-URL: Homepage, https://github.com/FrewtyPebbles/Neat-Object-Notation/tree/neat-python
Project-URL: Bug Tracker, https://github.com/FrewtyPebbles/Neat-Object-Notation/issues
